{
    "swagger": "2.0",
    "info": {
        "contact": {}
    },
    "paths": {
        "/company": {
            "post": {
                "description": "Create a new company",
                "consumes": [
                    "application/json"
                ],
                "produces": [
                    "application/json"
                ],
                "tags": [
                    "Companies"
                ],
                "summary": "Create company",
                "parameters": [
                    {
                        "description": "Request body",
                        "name": "request",
                        "in": "body",
                        "required": true,
                        "schema": {
                            "$ref": "#/definitions/handler.CreateCompanyRequest"
                        }
                    }
                ],
                "responses": {
                    "200": {
                        "description": "OK",
                        "schema": {
                            "$ref": "#/definitions/handler.CreateCompanyResponse"
                        }
                    },
                    "400": {
                        "description": "Bad Request",
                        "schema": {
                            "$ref": "#/definitions/handler.ErrorResponse"
                        }
                    },
                    "500": {
                        "description": "Internal Server Error",
                        "schema": {
                            "$ref": "#/definitions/handler.ErrorResponse"
                        }
                    }
                }
            }
        },
        "/holding": {
            "get": {
                "description": "Show a holding",
                "consumes": [
                    "application/json"
                ],
                "produces": [
                    "application/json"
                ],
                "tags": [
                    "Holdings"
                ],
                "summary": "Show holding",
                "parameters": [
                    {
                        "type": "string",
                        "description": "Holding identification",
                        "name": "id",
                        "in": "query",
                        "required": true
                    }
                ],
                "responses": {
                    "200": {
                        "description": "OK",
                        "schema": {
                            "$ref": "#/definitions/handler.ShowHoldingResponse"
                        }
                    },
                    "400": {
                        "description": "Bad Request",
                        "schema": {
                            "$ref": "#/definitions/handler.ErrorResponse"
                        }
                    },
                    "404": {
                        "description": "Not Found",
                        "schema": {
                            "$ref": "#/definitions/handler.ErrorResponse"
                        }
                    }
                }
            },
            "put": {
                "description": "Update a holding",
                "consumes": [
                    "application/json"
                ],
                "produces": [
                    "application/json"
                ],
                "tags": [
                    "Holdings"
                ],
                "summary": "Update holding",
                "parameters": [
                    {
                        "type": "string",
                        "description": "Holding identification",
                        "name": "id",
                        "in": "query",
                        "required": true
                    },
                    {
                        "description": "Holding data to Update",
                        "name": "opening",
                        "in": "body",
                        "required": true,
                        "schema": {
                            "$ref": "#/definitions/handler.UpdateOpeningRequest"
                        }
                    }
                ],
                "responses": {
                    "200": {
                        "description": "OK",
                        "schema": {
                            "$ref": "#/definitions/handler.UpdateHoldingResponse"
                        }
                    },
                    "400": {
                        "description": "Bad Request",
                        "schema": {
                            "$ref": "#/definitions/handler.ErrorResponse"
                        }
                    },
                    "404": {
                        "description": "Not Found",
                        "schema": {
                            "$ref": "#/definitions/handler.ErrorResponse"
                        }
                    },
                    "500": {
                        "description": "Internal Server Error",
                        "schema": {
                            "$ref": "#/definitions/handler.ErrorResponse"
                        }
                    }
                }
            },
            "post": {
                "description": "Create a new holding",
                "consumes": [
                    "application/json"
                ],
                "produces": [
                    "application/json"
                ],
                "tags": [
                    "Holdings"
                ],
                "summary": "Create holding",
                "parameters": [
                    {
                        "description": "Request body",
                        "name": "request",
                        "in": "body",
                        "required": true,
                        "schema": {
                            "$ref": "#/definitions/handler.CreateHoldingRequest"
                        }
                    }
                ],
                "responses": {
                    "200": {
                        "description": "OK",
                        "schema": {
                            "$ref": "#/definitions/handler.CreateHoldingResponse"
                        }
                    },
                    "400": {
                        "description": "Bad Request",
                        "schema": {
                            "$ref": "#/definitions/handler.ErrorResponse"
                        }
                    },
                    "500": {
                        "description": "Internal Server Error",
                        "schema": {
                            "$ref": "#/definitions/handler.ErrorResponse"
                        }
                    }
                }
            },
            "delete": {
                "description": "Delete a holding",
                "consumes": [
                    "application/json"
                ],
                "produces": [
                    "application/json"
                ],
                "tags": [
                    "Holdings"
                ],
                "summary": "Delete holding",
                "parameters": [
                    {
                        "type": "string",
                        "description": "Holding identification",
                        "name": "id",
                        "in": "query",
                        "required": true
                    }
                ],
                "responses": {
                    "200": {
                        "description": "OK",
                        "schema": {
                            "$ref": "#/definitions/handler.DeleteHoldingResponse"
                        }
                    },
                    "400": {
                        "description": "Bad Request",
                        "schema": {
                            "$ref": "#/definitions/handler.ErrorResponse"
                        }
                    },
                    "404": {
                        "description": "Not Found",
                        "schema": {
                            "$ref": "#/definitions/handler.ErrorResponse"
                        }
                    }
                }
            }
        },
        "/holdings": {
            "get": {
                "description": "List all holdings",
                "consumes": [
                    "application/json"
                ],
                "produces": [
                    "application/json"
                ],
                "tags": [
                    "Holdings"
                ],
                "summary": "List holdings",
                "responses": {
                    "200": {
                        "description": "OK",
                        "schema": {
                            "$ref": "#/definitions/handler.ListHoldingsResponse"
                        }
                    },
                    "500": {
                        "description": "Internal Server Error",
                        "schema": {
                            "$ref": "#/definitions/handler.ErrorResponse"
                        }
                    }
                }
            }
        },
        "/opening": {
            "get": {
                "description": "Show a job opening",
                "consumes": [
                    "application/json"
                ],
                "produces": [
                    "application/json"
                ],
                "tags": [
                    "Openings"
                ],
                "summary": "Show opening",
                "parameters": [
                    {
                        "type": "string",
                        "description": "Opening identification",
                        "name": "id",
                        "in": "query",
                        "required": true
                    }
                ],
                "responses": {
                    "200": {
                        "description": "OK",
                        "schema": {
                            "$ref": "#/definitions/handler.ShowOpeningResponse"
                        }
                    },
                    "400": {
                        "description": "Bad Request",
                        "schema": {
                            "$ref": "#/definitions/handler.ErrorResponse"
                        }
                    },
                    "404": {
                        "description": "Not Found",
                        "schema": {
                            "$ref": "#/definitions/handler.ErrorResponse"
                        }
                    }
                }
            },
            "put": {
                "description": "Update a job opening",
                "consumes": [
                    "application/json"
                ],
                "produces": [
                    "application/json"
                ],
                "tags": [
                    "Openings"
                ],
                "summary": "Update opening",
                "parameters": [
                    {
                        "type": "string",
                        "description": "Opening identification",
                        "name": "id",
                        "in": "query",
                        "required": true
                    },
                    {
                        "description": "Opening data to Update",
                        "name": "opening",
                        "in": "body",
                        "required": true,
                        "schema": {
                            "$ref": "#/definitions/handler.UpdateOpeningRequest"
                        }
                    }
                ],
                "responses": {
                    "200": {
                        "description": "OK",
                        "schema": {
                            "$ref": "#/definitions/handler.UpdateOpeningResponse"
                        }
                    },
                    "400": {
                        "description": "Bad Request",
                        "schema": {
                            "$ref": "#/definitions/handler.ErrorResponse"
                        }
                    },
                    "404": {
                        "description": "Not Found",
                        "schema": {
                            "$ref": "#/definitions/handler.ErrorResponse"
                        }
                    },
                    "500": {
                        "description": "Internal Server Error",
                        "schema": {
                            "$ref": "#/definitions/handler.ErrorResponse"
                        }
                    }
                }
            },
            "post": {
                "description": "Create a new job opening",
                "consumes": [
                    "application/json"
                ],
                "produces": [
                    "application/json"
                ],
                "tags": [
                    "Openings"
                ],
                "summary": "Create opening",
                "parameters": [
                    {
                        "description": "Request body",
                        "name": "request",
                        "in": "body",
                        "required": true,
                        "schema": {
                            "$ref": "#/definitions/handler.CreateOpeningRequest"
                        }
                    }
                ],
                "responses": {
                    "200": {
                        "description": "OK",
                        "schema": {
                            "$ref": "#/definitions/handler.CreateOpeningResponse"
                        }
                    },
                    "400": {
                        "description": "Bad Request",
                        "schema": {
                            "$ref": "#/definitions/handler.ErrorResponse"
                        }
                    },
                    "500": {
                        "description": "Internal Server Error",
                        "schema": {
                            "$ref": "#/definitions/handler.ErrorResponse"
                        }
                    }
                }
            },
            "delete": {
                "description": "Delete a job opening",
                "consumes": [
                    "application/json"
                ],
                "produces": [
                    "application/json"
                ],
                "tags": [
                    "Openings"
                ],
                "summary": "Delete opening",
                "parameters": [
                    {
                        "type": "string",
                        "description": "Opening identification",
                        "name": "id",
                        "in": "query",
                        "required": true
                    }
                ],
                "responses": {
                    "200": {
                        "description": "OK",
                        "schema": {
                            "$ref": "#/definitions/handler.DeleteOpeningResponse"
                        }
                    },
                    "400": {
                        "description": "Bad Request",
                        "schema": {
                            "$ref": "#/definitions/handler.ErrorResponse"
                        }
                    },
                    "404": {
                        "description": "Not Found",
                        "schema": {
                            "$ref": "#/definitions/handler.ErrorResponse"
                        }
                    }
                }
            }
        },
        "/openings": {
            "get": {
                "description": "List all job openings",
                "consumes": [
                    "application/json"
                ],
                "produces": [
                    "application/json"
                ],
                "tags": [
                    "Openings"
                ],
                "summary": "List openings",
                "responses": {
                    "200": {
                        "description": "OK",
                        "schema": {
                            "$ref": "#/definitions/handler.ListOpeningsResponse"
                        }
                    },
                    "500": {
                        "description": "Internal Server Error",
                        "schema": {
                            "$ref": "#/definitions/handler.ErrorResponse"
                        }
                    }
                }
            }
        }
    },
    "definitions": {
        "handler.CreateCompanyRequest": {
            "type": "object",
            "properties": {
                "holding_id": {
                    "type": "integer"
                },
                "name": {
                    "type": "string"
                }
            }
        },
        "handler.CreateCompanyResponse": {
            "type": "object",
            "properties": {
                "data": {
                    "$ref": "#/definitions/schemas.CompanyResponse"
                },
                "message": {
                    "type": "string"
                }
            }
        },
        "handler.CreateHoldingRequest": {
            "type": "object",
            "properties": {
                "name": {
                    "type": "string"
                }
            }
        },
        "handler.CreateHoldingResponse": {
            "type": "object",
            "properties": {
                "data": {
                    "$ref": "#/definitions/schemas.HoldingResponse"
                },
                "message": {
                    "type": "string"
                }
            }
        },
        "handler.CreateOpeningRequest": {
            "type": "object",
            "properties": {
                "company": {
                    "type": "string"
                },
                "link": {
                    "type": "string"
                },
                "location": {
                    "type": "string"
                },
                "remote": {
                    "type": "boolean"
                },
                "role": {
                    "type": "string"
                },
                "salary": {
                    "type": "integer"
                }
            }
        },
        "handler.CreateOpeningResponse": {
            "type": "object",
            "properties": {
                "data": {
                    "$ref": "#/definitions/schemas.OpeningResponse"
                },
                "message": {
                    "type": "string"
                }
            }
        },
        "handler.DeleteHoldingResponse": {
            "type": "object",
            "properties": {
                "data": {
                    "$ref": "#/definitions/schemas.HoldingResponse"
                },
                "message": {
                    "type": "string"
                }
            }
        },
        "handler.DeleteOpeningResponse": {
            "type": "object",
            "properties": {
                "data": {
                    "$ref": "#/definitions/schemas.OpeningResponse"
                },
                "message": {
                    "type": "string"
                }
            }
        },
        "handler.ErrorResponse": {
            "type": "object",
            "properties": {
                "errorCode": {
                    "type": "string"
                },
                "message": {
                    "type": "string"
                }
            }
        },
        "handler.ListHoldingsResponse": {
            "type": "object",
            "properties": {
                "data": {
                    "type": "array",
                    "items": {
                        "$ref": "#/definitions/schemas.HoldingResponse"
                    }
                },
                "message": {
                    "type": "string"
                }
            }
        },
        "handler.ListOpeningsResponse": {
            "type": "object",
            "properties": {
                "data": {
                    "type": "array",
                    "items": {
                        "$ref": "#/definitions/schemas.OpeningResponse"
                    }
                },
                "message": {
                    "type": "string"
                }
            }
        },
        "handler.ShowHoldingResponse": {
            "type": "object",
            "properties": {
                "data": {
                    "$ref": "#/definitions/schemas.HoldingResponse"
                },
                "message": {
                    "type": "string"
                }
            }
        },
        "handler.ShowOpeningResponse": {
            "type": "object",
            "properties": {
                "data": {
                    "$ref": "#/definitions/schemas.OpeningResponse"
                },
                "message": {
                    "type": "string"
                }
            }
        },
        "handler.UpdateHoldingResponse": {
            "type": "object",
            "properties": {
                "data": {
                    "$ref": "#/definitions/schemas.HoldingResponse"
                },
                "message": {
                    "type": "string"
                }
            }
        },
        "handler.UpdateOpeningRequest": {
            "type": "object",
            "properties": {
                "company": {
                    "type": "string"
                },
                "link": {
                    "type": "string"
                },
                "location": {
                    "type": "string"
                },
                "remote": {
                    "type": "boolean"
                },
                "role": {
                    "type": "string"
                },
                "salary": {
                    "type": "integer"
                }
            }
        },
        "handler.UpdateOpeningResponse": {
            "type": "object",
            "properties": {
                "data": {
                    "$ref": "#/definitions/schemas.OpeningResponse"
                },
                "message": {
                    "type": "string"
                }
            }
        },
        "schemas.Company": {
            "type": "object",
            "properties": {
                "holdingID": {
                    "type": "integer"
                },
                "name": {
                    "type": "string"
                }
            }
        },
        "schemas.CompanyResponse": {
            "type": "object",
            "properties": {
                "createdAt": {
                    "type": "string"
                },
                "deletedAt": {
                    "type": "string"
                },
                "holdingId": {
                    "type": "integer"
                },
                "id": {
                    "type": "integer"
                },
                "name": {
                    "type": "string"
                },
                "updatedAt": {
                    "type": "string"
                }
            }
        },
        "schemas.HoldingResponse": {
            "type": "object",
            "properties": {
                "company": {
                    "type": "array",
                    "items": {
                        "$ref": "#/definitions/schemas.Company"
                    }
                },
                "createdAt": {
                    "type": "string"
                },
                "deletedAt": {
                    "type": "string"
                },
                "id": {
                    "type": "integer"
                },
                "name": {
                    "type": "string"
                },
                "updatedAt": {
                    "type": "string"
                }
            }
        },
        "schemas.OpeningResponse": {
            "type": "object",
            "properties": {
                "company": {
                    "type": "string"
                },
                "createdAt": {
                    "type": "string"
                },
                "deletedAt": {
                    "type": "string"
                },
                "id": {
                    "type": "integer"
                },
                "link": {
                    "type": "string"
                },
                "location": {
                    "type": "string"
                },
                "remote": {
                    "type": "boolean"
                },
                "role": {
                    "type": "string"
                },
                "salary": {
                    "type": "integer"
                },
                "updatedAt": {
                    "type": "string"
                }
            }
        }
    }
}